[
  {
    "issuer": "Scorpio",
    "receier": "Acerkaio",
    "message": "Hello >_<",
    "timestamp": 1695632306335
  },
  {
    "issuer": "Acerkaio",
    "receier": "Scorpio",
    "message": "cnm",
    "timestamp": 1695648902809
  },
  {
    "issuer": "Fcersoka",
    "receier": "Scorpio",
    "message": "cnm",
    "timestamp": 1695649598399
  },
  {
    "issuer": "Fcersoka",
    "receier": "Scorpio",
    "message": "gdfgfvisdjughusidfhgushdfxu",
    "timestamp": 1695649623369
  },
  {
    "issuer": "Fcersoka",
    "receier": "Scorpio",
    "message": "efnshdbfudfg",
    "timestamp": 1695649666887
  },
  {
    "issuer": "Acerkaio",
    "receier": "Fcersoka",
    "message": "你是煞笔\n",
    "timestamp": 1695729611695
  },
  {
    "issuer": "Acerkaio",
    "receier": "Scorpio",
    "message": "cnm",
    "timestamp": 1695729614505
  },
  {
    "issuer": "Acerkaio",
    "receier": "Scorpio",
    "message": "cnm",
    "timestamp": 1695729615464
  },
  {
    "issuer": "Acerkaio",
    "receier": "Scorpio",
    "message": "cnm",
    "timestamp": 1695729618885
  },
  {
    "issuer": "Acerkaio",
    "receier": "Scorpio",
    "message": "cnm",
    "timestamp": 1695729619432
  },
  {
    "issuer": "Acerkaio",
    "receier": "Scorpio",
    "message": "cnm",
    "timestamp": 1695729619588
  },
  {
    "issuer": "Acerkaio",
    "receier": "Scorpio",
    "message": "cnm",
    "timestamp": 1695729619741
  },
  {
    "issuer": "Acerkaio",
    "receier": "Scorpio",
    "message": "cnm",
    "timestamp": 1695729619876
  },
  {
    "issuer": "Acerkaio",
    "receier": "Scorpio",
    "message": "cnm",
    "timestamp": 1695729619996
  },
  {
    "issuer": "Acerkaio",
    "receier": "Scorpio",
    "message": "cnm",
    "timestamp": 1695729620109
  },
  {
    "issuer": "Acerkaio",
    "receier": "Scorpio",
    "message": "cnm",
    "timestamp": 1695729620342
  },
  {
    "issuer": "Acerkaio",
    "receier": "Scorpio",
    "message": "cnm",
    "timestamp": 1695729620559
  },
  {
    "issuer": "Acerkaio",
    "receier": "Scorpio",
    "message": "cnm",
    "timestamp": 1695729620684
  },
  {
    "issuer": "Acerkaio",
    "receier": "Scorpio",
    "message": "cnm",
    "timestamp": 1695729620926
  },
  {
    "issuer": "Acerkaio",
    "receier": "Scorpio",
    "message": "cnm",
    "timestamp": 1695729621047
  },
  {
    "issuer": "Acerkaio",
    "receier": "Scorpio",
    "message": "cnm",
    "timestamp": 1695729621160
  }
]